fotoparadies/__init__.py
fotoparadies/fotoparadies.py
fotoparadies/main.py
fotoparadies-0.1.1.dist-info/entry_points.txt
fotoparadies-0.1.1.dist-info/LICENSE
fotoparadies-0.1.1.dist-info/WHEEL
fotoparadies-0.1.1.dist-info/METADATA
fotoparadies-0.1.1.dist-info/RECORD
