Metadata-Version: 2.1
Name: fotoparadies
Version: 0.1.1
Summary: Shows status of fotoparadies orders
Home-page: https://github.com/hija/fotoparadies
License: MIT
Author: hilko
Requires-Python: >=3.9,<4.0
Classifier: License :: OSI Approved :: MIT License
Classifier: Programming Language :: Python :: 3
Classifier: Programming Language :: Python :: 3.9
Classifier: Programming Language :: Python :: 3.10
Requires-Dist: platformdirs (>=2.5.2,<3.0.0)
Requires-Dist: requests (>=2.28.1,<3.0.0)
Requires-Dist: typer[all] (>=0.6.1,<0.7.0)
Project-URL: Bug Tracker, https://github.com/hija/fotoparadies/issues
Project-URL: Repository, https://github.com/hija/fotoparadies
